[{"lx":56,"ly":66,"mx":56,"my":65},{"lx":55,"ly":63,"mx":56,"my":66},{"lx":54,"ly":59,"mx":55,"my":63},{"lx":54,"ly":56,"mx":54,"my":59},{"lx":54,"ly":53,"mx":54,"my":56},{"lx":54,"ly":50,"mx":54,"my":53},{"lx":54,"ly":47,"mx":54,"my":50},{"lx":54,"ly":43,"mx":54,"my":47},{"lx":56,"ly":41,"mx":54,"my":43},{"lx":59,"ly":37,"mx":56,"my":41},{"lx":61,"ly":34,"mx":59,"my":37},{"lx":65,"ly":30,"mx":61,"my":34},{"lx":67,"ly":26,"mx":65,"my":30},{"lx":70,"ly":25,"mx":67,"my":26},{"lx":71,"ly":25,"mx":70,"my":25},{"lx":72,"ly":28,"mx":71,"my":25},{"lx":74,"ly":38,"mx":72,"my":28},{"lx":74,"ly":45,"mx":74,"my":38},{"lx":74,"ly":53,"mx":74,"my":45},{"lx":74,"ly":59,"mx":74,"my":53},{"lx":74,"ly":63,"mx":74,"my":59},{"lx":74,"ly":64,"mx":74,"my":63},{"lx":74,"ly":65,"mx":74,"my":64},{"lx":74,"ly":66,"mx":74,"my":65},{"lx":75,"ly":66,"mx":74,"my":66},{"lx":75,"ly":65,"mx":75,"my":66},{"lx":76,"ly":64,"mx":75,"my":65},{"lx":77,"ly":64,"mx":76,"my":64},{"lx":78,"ly":64,"mx":77,"my":64},{"lx":78,"ly":65,"mx":78,"my":64},{"lx":79,"ly":65,"mx":78,"my":65},{"lx":79,"ly":66,"mx":79,"my":65},{"lx":80,"ly":66,"mx":79,"my":66},{"lx":81,"ly":66,"mx":80,"my":66},{"lx":82,"ly":66,"mx":81,"my":66},{"lx":84,"ly":66,"mx":82,"my":66},{"lx":86,"ly":66,"mx":84,"my":66},{"lx":88,"ly":65,"mx":86,"my":66},{"lx":92,"ly":63,"mx":88,"my":65},{"lx":94,"ly":60,"mx":92,"my":63},{"lx":99,"ly":56,"mx":94,"my":60},{"lx":103,"ly":53,"mx":99,"my":56},{"lx":105,"ly":53,"mx":103,"my":53},{"lx":105,"ly":52,"mx":105,"my":53},{"lx":106,"ly":52,"mx":105,"my":52},{"lx":107,"ly":52,"mx":106,"my":52},{"lx":109,"ly":54,"mx":107,"my":52},{"lx":110,"ly":58,"mx":109,"my":54},{"lx":110,"ly":62,"mx":110,"my":58},{"lx":111,"ly":64,"mx":110,"my":62},{"lx":111,"ly":67,"mx":111,"my":64},{"lx":112,"ly":70,"mx":111,"my":67},{"lx":113,"ly":72,"mx":112,"my":70},{"lx":113,"ly":73,"mx":113,"my":72},{"lx":113,"ly":74,"mx":113,"my":73},{"lx":114,"ly":74,"mx":113,"my":74},{"lx":115,"ly":73,"mx":114,"my":74},{"lx":116,"ly":72,"mx":115,"my":73},{"lx":117,"ly":72,"mx":116,"my":72},{"lx":118,"ly":71,"mx":117,"my":72},{"lx":119,"ly":70,"mx":118,"my":71},{"lx":120,"ly":70,"mx":119,"my":70},{"lx":121,"ly":69,"mx":120,"my":70},{"lx":122,"ly":69,"mx":121,"my":69},{"lx":123,"ly":69,"mx":122,"my":69},{"lx":124,"ly":69,"mx":123,"my":69},{"lx":125,"ly":69,"mx":124,"my":69},{"lx":126,"ly":69,"mx":125,"my":69},{"lx":127,"ly":70,"mx":126,"my":69},{"lx":128,"ly":71,"mx":127,"my":70},{"lx":129,"ly":72,"mx":128,"my":71},{"lx":130,"ly":73,"mx":129,"my":72},{"lx":131,"ly":74,"mx":130,"my":73},{"lx":132,"ly":74,"mx":131,"my":74},{"lx":134,"ly":74,"mx":132,"my":74},{"lx":135,"ly":73,"mx":134,"my":74},{"lx":136,"ly":71,"mx":135,"my":73},{"lx":139,"ly":68,"mx":136,"my":71},{"lx":140,"ly":66,"mx":139,"my":68},{"lx":141,"ly":65,"mx":140,"my":66},{"lx":141,"ly":64,"mx":141,"my":65},{"lx":143,"ly":64,"mx":141,"my":64},{"lx":144,"ly":63,"mx":143,"my":64},{"lx":145,"ly":62,"mx":144,"my":63},{"lx":145,"ly":60,"mx":145,"my":62},{"lx":146,"ly":58,"mx":145,"my":60},{"lx":146,"ly":56,"mx":146,"my":58},{"lx":146,"ly":54,"mx":146,"my":56},{"lx":146,"ly":52,"mx":146,"my":54},{"lx":146,"ly":50,"mx":146,"my":52},{"lx":145,"ly":47,"mx":146,"my":50},{"lx":144,"ly":45,"mx":145,"my":47},{"lx":143,"ly":43,"mx":144,"my":45},{"lx":142,"ly":42,"mx":143,"my":43},{"lx":141,"ly":40,"mx":142,"my":42},{"lx":140,"ly":40,"mx":141,"my":40},{"lx":139,"ly":39,"mx":140,"my":40},{"lx":138,"ly":38,"mx":139,"my":39},{"lx":136,"ly":38,"mx":138,"my":38},{"lx":134,"ly":38,"mx":136,"my":38},{"lx":133,"ly":38,"mx":134,"my":38},{"lx":131,"ly":38,"mx":133,"my":38},{"lx":128,"ly":40,"mx":131,"my":38},{"lx":126,"ly":42,"mx":128,"my":40},{"lx":124,"ly":43,"mx":126,"my":42},{"lx":121,"ly":46,"mx":124,"my":43},{"lx":119,"ly":48,"mx":121,"my":46},{"lx":117,"ly":50,"mx":119,"my":48},{"lx":114,"ly":53,"mx":117,"my":50},{"lx":111,"ly":55,"mx":114,"my":53},{"lx":108,"ly":58,"mx":111,"my":55},{"lx":106,"ly":60,"mx":108,"my":58},{"lx":104,"ly":62,"mx":106,"my":60},{"lx":102,"ly":64,"mx":104,"my":62},{"lx":101,"ly":66,"mx":102,"my":64},{"lx":100,"ly":67,"mx":101,"my":66},{"lx":100,"ly":68,"mx":100,"my":67},{"lx":100,"ly":69,"mx":100,"my":68},{"lx":100,"ly":70,"mx":100,"my":69},{"lx":100,"ly":71,"mx":100,"my":70},{"lx":103,"ly":74,"mx":100,"my":71},{"lx":108,"ly":78,"mx":103,"my":74},{"lx":114,"ly":83,"mx":108,"my":78},{"lx":122,"ly":86,"mx":114,"my":83},{"lx":129,"ly":89,"mx":122,"my":86},{"lx":134,"ly":92,"mx":129,"my":89},{"lx":138,"ly":93,"mx":134,"my":92},{"lx":141,"ly":93,"mx":138,"my":93},{"lx":144,"ly":93,"mx":141,"my":93},{"lx":147,"ly":93,"mx":144,"my":93},{"lx":149,"ly":90,"mx":147,"my":93},{"lx":152,"ly":87,"mx":149,"my":90},{"lx":154,"ly":83,"mx":152,"my":87},{"lx":154,"ly":78,"mx":154,"my":83},{"lx":155,"ly":72,"mx":154,"my":78},{"lx":155,"ly":67,"mx":155,"my":72},{"lx":156,"ly":63,"mx":155,"my":67},{"lx":156,"ly":61,"mx":156,"my":63},{"lx":156,"ly":60,"mx":156,"my":61},{"lx":156,"ly":59,"mx":156,"my":60},{"lx":155,"ly":61,"mx":156,"my":59},{"lx":154,"ly":63,"mx":155,"my":61},{"lx":153,"ly":64,"mx":154,"my":63},{"lx":152,"ly":67,"mx":153,"my":64}]